{
  "fullnames": {
    "PLN": "polski złoty",
    "EUR": "euro",
    "USD": "dolar amerykański",
    "GBP": "funt brytyjski",
    "CHF": "frank szwajcarski",
    "AUD": "dolar australijski",
    "BGN": "lew bułgarski",
    "BRL": "real brazylijski",
    "CAD": "dolar kanadyjski",
    "CNY": "chiński Juan (Renminbi)",
    "CZK": "korona czeska",
    "DKK": "korona duńska",
    "HKD": "dolar hongkoński",
    "HRK": "kuna chorwacka",
    "HUF": "forint węgierski",
    "IDR": "rupia indonezyjska",
    "ILS": "nowy szekel izraelski",
    "INR": "rupia indyjska",
    "JPY": "jen japoński",
    "KRW": "won południowokoreański",
    "MXN": "peso meksykańskie",
    "MYR": "ringgit malezyjski",
    "NOK": "korona norweska",
    "NZD": "dolar nowozelandzki",
    "PHP": "peso filipińskie",
    "RON": "nowa leja rumuńska",
    "RUB": "rubel rosyjski",
    "SEK": "korona szwedzka",
    "SGD": "dolar singapurski",
    "THB": "baht tajski",
    "TRY": "nowa lira turecka",
    "ZAR": "rand południowoafrykański"
  }
}
